{
  "sites": [
    {
      "key": "CK资源|AV",
      "name": "CK资源|AV",
      "type": 1,
      "api": "https://ckzy.me/api.php/provide/vod/",
      "searchable": 1,
      "quickSearch": 1
    },
    {
    "key": "KK写真|AV",
    "name": "KK写真|AV",
    "type": 1,
    "api": "https://kkzy.me/api.php/provide/vod/",
    "searchable": 1,
    "quickSearch": 1
    },
    {
    "key": "乐播资源|AV",
    "name": "乐播资源|AV",
    "type": 1,
    "api": "https://lbapi9.com/api.php/provide/vod/",
    "searchable": 1,
    "quickSearch": 1
    },
    {
    "key": "老鸭资源|AV",
    "name": "老鸭资源|AV",
    "type": 1,
    "api": "https://api.apilyzy.com/api.php/provide/vod/",
    "searchable": 1,
    "quickSearch": 1
    },
    {
    "key": "探探资源|AV",
    "name": "探探资源|AV",
    "type": 1,
    "api": "https://apittzy.com/api.php/provide/vod/",
    "searchable": 1,
    "quickSearch": 1
    },
    {
    "key": "色猫资源|AV",
    "name": "色猫资源|AV",
    "type": 1,
    "api": "https://api.maozyapi.com/inc/apijson_vod.php",
    "searchable": 1,
    "quickSearch": 1
    },
    {
    "key": "易看资源|AV",
    "name": "易看资源|AV",
    "type": 1,
    "api": "https://api.yikanapi.com/api.php/provide/vod/",
    "searchable": 1,
    "quickSearch": 1
    },
    {
    "key": "森林资源|AV",
    "name": "森林资源|AV",
    "type": 1,
    "api": "https://slapibf.com/api.php/provide/vod/",
    "searchable": 1,
    "quickSearch": 1
    },
    {
    "key": "精品资源|AV",
    "name": "辣椒资源|AV",
    "type": 1,
    "api": "https://www.jingpinx.com/api.php/provide/vod/",
    "searchable": 1,
    "quickSearch": 1
    },
    {
    "key": "老色逼资源|AV",
    "name": "老色逼资源|AV",
    "type": 1,
    "api": "https://apilsbzy1.com/api.php/provide/vod/",
    "searchable": 1,
    "quickSearch": 1
    },
    {
    "key": "黄瓜资源|AV",
    "name": "黄瓜资源|AV",
    "type": 1,
    "api": "https://www.zy018.com/api.php/provide/vod/",
    "searchable": 1,
    "quickSearch": 1
    },
    {
    "key": "草榴资源|AV",
    "name": "草榴资源|AV",
    "type": 1,
    "api": "https://www.caoliuzyw.com/api.php/provide/vod/",
    "searchable": 1,
    "quickSearch": 1
    },
    {
    "key": "色色虎资源|AV",
    "name": "色色虎资源|AV",
    "type": 1,
    "api": "https://apisesehuzy.com/api.php/provide/vod/",
    "searchable": 1,
    "quickSearch": 1
    },
    {
    "key": "奶香香|AV",
    "name": "奶香香|AV",
    "type": 1,
    "api": "https://naixxzy.com/api.php/provide/vod/",
    "searchable": 1,
    "quickSearch": 1
    },
    {
    "key": "玉兔资源|AV",
    "name": "玉兔资源|AV",
    "type": 1,
    "api": "https://apiyutu.com/api.php/provide/vod/",
    "searchable": 1,
    "quickSearch": 1
    },
    {
    "key": "奥斯卡资源|AV",
    "name": "奥斯卡资源|AV",
    "type": 1,
    "api": "https://aosikazy.com/api.php/provide/vod/",
    "searchable": 1,
    "quickSearch": 1
    }
    ]
    }